odoo/addons/sale_automatic_workflow_invoice_default_value/README.rst
odoo/addons/sale_automatic_workflow_invoice_default_value/__init__.py
odoo/addons/sale_automatic_workflow_invoice_default_value/__manifest__.py
odoo/addons/sale_automatic_workflow_invoice_default_value/i18n/es.po
odoo/addons/sale_automatic_workflow_invoice_default_value/i18n/fr.po
odoo/addons/sale_automatic_workflow_invoice_default_value/i18n/it.po
odoo/addons/sale_automatic_workflow_invoice_default_value/i18n/sale_automatic_workflow_invoice_default_value.pot
odoo/addons/sale_automatic_workflow_invoice_default_value/models/__init__.py
odoo/addons/sale_automatic_workflow_invoice_default_value/models/automatic_workflow_invoice_default_value.py
odoo/addons/sale_automatic_workflow_invoice_default_value/models/automatic_workflow_job.py
odoo/addons/sale_automatic_workflow_invoice_default_value/models/sale_workflow_process.py
odoo/addons/sale_automatic_workflow_invoice_default_value/readme/CONTRIBUTORS.rst
odoo/addons/sale_automatic_workflow_invoice_default_value/readme/DESCRIPTION.rst
odoo/addons/sale_automatic_workflow_invoice_default_value/security/ir.model.access.csv
odoo/addons/sale_automatic_workflow_invoice_default_value/static/description/icon.png
odoo/addons/sale_automatic_workflow_invoice_default_value/static/description/index.html
odoo/addons/sale_automatic_workflow_invoice_default_value/tests/__init__.py
odoo/addons/sale_automatic_workflow_invoice_default_value/tests/test_automatic_workflow_invoice_default_value.py
odoo/addons/sale_automatic_workflow_invoice_default_value/views/sale_workflow_process.xml
odoo14_addon_sale_automatic_workflow_invoice_default_value-14.0.1.0.1.dev7.dist-info/METADATA
odoo14_addon_sale_automatic_workflow_invoice_default_value-14.0.1.0.1.dev7.dist-info/WHEEL
odoo14_addon_sale_automatic_workflow_invoice_default_value-14.0.1.0.1.dev7.dist-info/top_level.txt
odoo14_addon_sale_automatic_workflow_invoice_default_value-14.0.1.0.1.dev7.dist-info/RECORD
